aws_lambda_decorators/__init__.py
aws_lambda_decorators/classes.py
aws_lambda_decorators/decoders.py
aws_lambda_decorators/decorators.py
aws_lambda_decorators/utils.py
aws_lambda_decorators/validators.py
aws_lambda_decorators-0.53.dist-info/LICENSE
aws_lambda_decorators-0.53.dist-info/METADATA
aws_lambda_decorators-0.53.dist-info/WHEEL
aws_lambda_decorators-0.53.dist-info/top_level.txt
aws_lambda_decorators-0.53.dist-info/RECORD
