Metadata-Version: 2.1
Name: aws-lambda-decorators
Version: 0.53
Summary: A set of python decorators to simplify aws python lambda development
Home-page: https://github.com/gridsmartercities/aws-lambda-decorators
Author: Grid Smarter Cities
Author-email: open-source@gridsmartercities.com
License: MIT
Keywords: aws lambda decorator
Platform: UNKNOWN
Classifier: Intended Audience :: Developers
Classifier: Development Status :: 4 - Beta
Classifier: Programming Language :: Python :: 3
Classifier: License :: OSI Approved :: MIT License
Classifier: Operating System :: OS Independent
Classifier: Natural Language :: English
License-File: LICENSE
Requires-Dist: boto3
Requires-Dist: PyJWT
Requires-Dist: schema
